{
  "article_id": "sysu_20251015_2037",
  "title": "祝贺！中山大学刘志伟教授获评广东省民族团结进步模范个人",
  "publish_time": "2025-10-15 20:37",
  "account": "中山大学",
  "publish_location": "广东",
  "article_types": [
    "人物荣誉类",
    "教师人物类",
    "学术贡献类",
    "民族团结进步类"
  ],
  "keywords": [
    "刘志伟",
    "民族团结进步",
    "历史人类学",
    "中华民族共同体",
    "广东卷",
    "人才培养"
  ],
  "summary": "文章报道刘志伟教授获评广东省民族团结进步模范个人，并系统梳理其历史人类学研究、史料编纂、基地建设和人才培养贡献。",
  "communication_goal": "以荣誉为入口呈现学者履历、原创学术范式、国家工程和育人成果，说明荣誉背后的长期贡献。",
  "facts": [
    {
      "id": "f001",
      "fact": "10月14日上午，全省民族团结进步表彰大会在广州召开。",
      "type": "会议",
      "time": "2025-10-15 20:37",
      "subject": "祝贺！中山大学刘志伟教授获评广东省民族团结进步模范个人",
      "object": "10月14日上午，全省民族团结进步表彰大会在广州召开。",
      "importance": "高",
      "can_reuse": true,
      "risk": "中",
      "source_paragraph_id": "p001",
      "source_quote": "10月14日上午，全省民族团结进步表彰大会在广州召开",
      "confidence": "high"
    },
    {
      "id": "f002",
      "fact": "刘志伟教授获评“广东省民族团结进步模范个人”。",
      "type": "荣誉",
      "time": "2025-10-15 20:37",
      "subject": "祝贺！中山大学刘志伟教授获评广东省民族团结进步模范个人",
      "object": "刘志伟教授获评“广东省民族团结进步模范个人”。",
      "importance": "高",
      "can_reuse": true,
      "risk": "中",
      "source_paragraph_id": "p001",
      "source_quote": "刘志伟获评“广东省民族团结进步模范个人”",
      "confidence": "high"
    },
    {
      "id": "f003",
      "fact": "刘志伟1983年毕业于中山大学历史学系，此后一直从事明清社会经济史教学与研究。",
      "type": "履历",
      "time": "2025-10-15 20:37",
      "subject": "祝贺！中山大学刘志伟教授获评广东省民族团结进步模范个人",
      "object": "刘志伟1983年毕业于中山大学历史学系，此后一直从事明清社会经济史教学与研究。",
      "importance": "高",
      "can_reuse": true,
      "risk": "中",
      "source_paragraph_id": "p003",
      "source_quote": "1983年从中山大学历史学系毕业后，一直在中山大学从事明清社会经济史教学与研究",
      "confidence": "high"
    },
    {
      "id": "f004",
      "fact": "刘志伟现任中山大学铸牢中华民族共同体意识研究基地首席专家。",
      "type": "职务",
      "time": "2025-10-15 20:37",
      "subject": "祝贺！中山大学刘志伟教授获评广东省民族团结进步模范个人",
      "object": "刘志伟现任中山大学铸牢中华民族共同体意识研究基地首席专家。",
      "importance": "高",
      "can_reuse": true,
      "risk": "中",
      "source_paragraph_id": "p003",
      "source_quote": "中山大学铸牢中华民族共同体意识研究基地首席专家",
      "confidence": "high"
    },
    {
      "id": "f005",
      "fact": "刘志伟倡导并引领“历史人类学”研究路径，强调从中国历史文化中提炼“中国范式”。",
      "type": "学术贡献",
      "time": "2025-10-15 20:37",
      "subject": "祝贺！中山大学刘志伟教授获评广东省民族团结进步模范个人",
      "object": "刘志伟倡导并引领“历史人类学”研究路径，强调从中国历史文化中提炼“中国范式”。",
      "importance": "高",
      "can_reuse": true,
      "risk": "中",
      "source_paragraph_id": "p003",
      "source_quote": "他所倡导和引领的 “历史人类学” 研究路径",
      "confidence": "high"
    },
    {
      "id": "f006",
      "fact": "其团队将文献考证与实地访谈结合，探索“在历史中寻找中国”的路径。",
      "type": "方法",
      "time": "2025-10-15 20:37",
      "subject": "祝贺！中山大学刘志伟教授获评广东省民族团结进步模范个人",
      "object": "其团队将文献考证与实地访谈结合，探索“在历史中寻找中国”的路径。",
      "importance": "高",
      "can_reuse": true,
      "risk": "中",
      "source_paragraph_id": "p004",
      "source_quote": "将文献考证与实地访谈相结合",
      "confidence": "high"
    },
    {
      "id": "f007",
      "fact": "刘志伟以现代学术话语诠释“食货原理”，构建“贡赋体制经济”理论。",
      "type": "学术贡献",
      "time": "2025-10-15 20:37",
      "subject": "祝贺！中山大学刘志伟教授获评广东省民族团结进步模范个人",
      "object": "刘志伟以现代学术话语诠释“食货原理”，构建“贡赋体制经济”理论。",
      "importance": "高",
      "can_reuse": true,
      "risk": "中",
      "source_paragraph_id": "p005",
      "source_quote": "构建原创的“贡赋体制经济”理论",
      "confidence": "high"
    },
    {
      "id": "f008",
      "fact": "其华南宗族研究强调文化认同对凝聚中华民族的重要作用。",
      "type": "学术贡献",
      "time": "2025-10-15 20:37",
      "subject": "祝贺！中山大学刘志伟教授获评广东省民族团结进步模范个人",
      "object": "其华南宗族研究强调文化认同对凝聚中华民族的重要作用。",
      "importance": "高",
      "can_reuse": true,
      "risk": "中",
      "source_paragraph_id": "p005",
      "source_quote": "通过对华南宗族的研究 深刻揭示了文化认同 是凝聚中华民族的强大力量",
      "confidence": "high"
    },
    {
      "id": "f009",
      "fact": "刘志伟四十年来持续从事教书育人，并培养多位史学人才。",
      "type": "育人",
      "time": "2025-10-15 20:37",
      "subject": "祝贺！中山大学刘志伟教授获评广东省民族团结进步模范个人",
      "object": "刘志伟四十年来持续从事教书育人，并培养多位史学人才。",
      "importance": "高",
      "can_reuse": true,
      "risk": "中",
      "source_paragraph_id": "p005",
      "source_quote": "四十年来 他在教书育人的 岗位上",
      "confidence": "high"
    },
    {
      "id": "f010",
      "fact": "刘志伟主持《中华民族交往交流交融史料汇编·广东卷》编纂。",
      "type": "成果",
      "time": "2025-10-15 20:37",
      "subject": "祝贺！中山大学刘志伟教授获评广东省民族团结进步模范个人",
      "object": "刘志伟主持《中华民族交往交流交融史料汇编·广东卷》编纂。",
      "importance": "高",
      "can_reuse": true,
      "risk": "中",
      "source_paragraph_id": "p006",
      "source_quote": "《中华民族交往交流交融史料汇编· 广东卷》",
      "confidence": "high"
    },
    {
      "id": "f011",
      "fact": "《广东卷》编纂强调从静态身份转向动态认同过程。",
      "type": "方法",
      "time": "2025-10-15 20:37",
      "subject": "祝贺！中山大学刘志伟教授获评广东省民族团结进步模范个人",
      "object": "《广东卷》编纂强调从静态身份转向动态认同过程。",
      "importance": "高",
      "can_reuse": true,
      "risk": "中",
      "source_paragraph_id": "p007",
      "source_quote": "从“静态的身份” 转向“动态的认同过程”",
      "confidence": "high"
    },
    {
      "id": "f012",
      "fact": "《广东卷》编纂强调从精英政治深入民众日常。",
      "type": "方法",
      "time": "2025-10-15 20:37",
      "subject": "祝贺！中山大学刘志伟教授获评广东省民族团结进步模范个人",
      "object": "《广东卷》编纂强调从精英政治深入民众日常。",
      "importance": "高",
      "can_reuse": true,
      "risk": "中",
      "source_paragraph_id": "p007",
      "source_quote": "从“精英的政治” 深入“民众的日常”",
      "confidence": "high"
    },
    {
      "id": "f013",
      "fact": "《广东卷》编纂强调由地方特殊性阐释国家普遍性。",
      "type": "方法",
      "time": "2025-10-15 20:37",
      "subject": "祝贺！中山大学刘志伟教授获评广东省民族团结进步模范个人",
      "object": "《广东卷》编纂强调由地方特殊性阐释国家普遍性。",
      "importance": "高",
      "can_reuse": true,
      "risk": "中",
      "source_paragraph_id": "p007",
      "source_quote": "从“地方的特殊性” 阐释“国家的普遍性”",
      "confidence": "high"
    },
    {
      "id": "f014",
      "fact": "刘志伟带领三所广东高校团队在不到两年内完成六大分卷。",
      "type": "成果",
      "time": "2025-10-15 20:37",
      "subject": "祝贺！中山大学刘志伟教授获评广东省民族团结进步模范个人",
      "object": "刘志伟带领三所广东高校团队在不到两年内完成六大分卷。",
      "importance": "高",
      "can_reuse": true,
      "risk": "中",
      "source_paragraph_id": "p007",
      "source_quote": "在不到两年时间内 刘志伟率领来自三所广东高校的团队 高质高量完成六大分卷",
      "confidence": "high"
    },
    {
      "id": "f015",
      "fact": "2023年，中山大学历史人类学研究中心获批第二批四部委铸牢中华民族共同体意识研究基地。",
      "type": "机构",
      "time": "2025-10-15 20:37",
      "subject": "祝贺！中山大学刘志伟教授获评广东省民族团结进步模范个人",
      "object": "2023年，中山大学历史人类学研究中心获批第二批四部委铸牢中华民族共同体意识研究基地。",
      "importance": "高",
      "can_reuse": true,
      "risk": "中",
      "source_paragraph_id": "p007",
      "source_quote": "2023年，中山大学历史人类学研究中心获批 第二批四部委铸牢中华民族共同体意识研究基地",
      "confidence": "high"
    },
    {
      "id": "f016",
      "fact": "基地获得国家社科基金铸牢专项重大项目立项，并拓展跨区域跨学科合作。",
      "type": "项目",
      "time": "2025-10-15 20:37",
      "subject": "祝贺！中山大学刘志伟教授获评广东省民族团结进步模范个人",
      "object": "基地获得国家社科基金铸牢专项重大项目立项，并拓展跨区域跨学科合作。",
      "importance": "高",
      "can_reuse": true,
      "risk": "中",
      "source_paragraph_id": "p008",
      "source_quote": "获 得国家社科基金 铸牢专项重大项目",
      "confidence": "high"
    },
    {
      "id": "f017",
      "fact": "刘志伟推动形成涵盖历史学、人类学、民族学和考古学的跨学科团队。",
      "type": "团队",
      "time": "2025-10-15 20:37",
      "subject": "祝贺！中山大学刘志伟教授获评广东省民族团结进步模范个人",
      "object": "刘志伟推动形成涵盖历史学、人类学、民族学和考古学的跨学科团队。",
      "importance": "高",
      "can_reuse": true,
      "risk": "中",
      "source_paragraph_id": "p009",
      "source_quote": "凝聚了一支 跨学科高水平研究团队",
      "confidence": "high"
    },
    {
      "id": "f018",
      "fact": "刘志伟重视青年学者培养和学术阵地建设。",
      "type": "育人",
      "time": "2025-10-15 20:37",
      "subject": "祝贺！中山大学刘志伟教授获评广东省民族团结进步模范个人",
      "object": "刘志伟重视青年学者培养和学术阵地建设。",
      "importance": "高",
      "can_reuse": true,
      "risk": "中",
      "source_paragraph_id": "p009",
      "source_quote": "十分重视对青年学者的培养",
      "confidence": "high"
    }
  ],
  "structure": [
    {
      "summary": "交代表彰大会和获奖身份。",
      "section": "获奖信息",
      "function": "荣誉导入"
    },
    {
      "summary": "梳理刘志伟的教学研究经历和现任职务。",
      "section": "人物履历",
      "function": "背景建立"
    },
    {
      "summary": "从历史人类学、贡赋体制经济和华南宗族研究呈现三项贡献。",
      "section": "理论贡献",
      "function": "学术阐释"
    },
    {
      "summary": "说明史料汇编价值、三项指导思路和六大分卷成果。",
      "section": "广东卷编纂",
      "function": "工程展示"
    },
    {
      "summary": "呈现研究基地的理论范式、重大项目与合作网络。",
      "section": "基地建设",
      "function": "平台贡献"
    },
    {
      "summary": "说明跨学科团队、青年培养和学术阵地建设。",
      "section": "团队育人",
      "function": "价值收束"
    }
  ],
  "paragraph_functions": [
    {
      "paragraph_id": "p001",
      "display_text": "10月14日上午，全省民族团结进步表彰大会在广州召开，表彰广东省民族团结进步模范集体和模范个人。  **\n\n中山大学铸牢中华民族共同体意识研究基地首席专家、历史学系教授刘志伟获评“广东省民族团结进步模范个人”。  **",
      "normalized_text": "10月14日上午，全省民族团结进步表彰大会在广州召开，表彰广东省民族团结进步模范集体和模范个人。 中山大学铸牢中华民族共同体意识研究基地首席专家、历史学系教授刘志伟获评“广东省民族团结进步模范个人”。",
      "summary": "10月14日上午，全省民族团结进步表彰大会在广州召开，表彰广东省民族团结进步模范集体和模范个人。 中山大学铸牢中华民族共同体意识研究基地首席专家、历史学系教授刘…",
      "function_tags": [
        "结构提示",
        "核心事实",
        "人物叙事"
      ],
      "writing_method": "以具体时间、数字或对象增强信息可信度。",
      "reuse_value": "高"
    },
    {
      "paragraph_id": "p002",
      "display_text": "荣誉证书\n\n** 刘志伟教授简介  **",
      "normalized_text": "荣誉证书 刘志伟教授简介",
      "summary": "荣誉证书 刘志伟教授简介",
      "function_tags": [
        "结构提示",
        "人物叙事"
      ],
      "writing_method": "用短句推进信息，并保持公众号移动端阅读节奏。",
      "reuse_value": "高"
    },
    {
      "paragraph_id": "p003",
      "display_text": "刘志伟，中山大学历史学系教授，中山大学人文学科发展委员会主任，国家教材委历史学科专家委员会委员，中国社会史学会副会长，中国经济史学会中国古代经济史分委员会副主任。1983年从中山大学历史学系毕业后，一直在中山大学从事明清社会经济史教学与研究。2000-2008年任中山大学历史学系主任，2008-2015年任亚太研究院常务副院长，2010-2022年任中山大学历史人类学研究中心主任。现任《中华民族交往交流交融史》编撰委员会编委、中山大学铸牢中华民族共同体意识研究基地首席专家、中华民族交往交流交融史料汇编（广东卷）编委会常务副主任。\n\n** 理解中华民族共同体形成的理论基石  **\n\n刘志伟最卓越的学术贡献\n\n在于他深刻洞察到\n\n要真正理解中华民族共同体的形成\n\n必须摆脱长期以来\n\n史学界对西方理论的\n\n简单移植或被动修正\n\n转而从中国自身的历史和文化中\n\n提炼具有主体性\n\n以及强大解释力的\n\n** “中国范式”  **\n\n他所倡导和引领的\n\n** “历史人类学”  ** 研究路径\n\n正是这一学术自觉的集中体现\n\n对于理解中华民族共同体的形成\n\n其研究贡献主要体  现在三个方面：",
      "normalized_text": "刘志伟，中山大学历史学系教授，中山大学人文学科发展委员会主任，国家教材委历史学科专家委员会委员，中国社会史学会副会长，中国经济史学会中国古代经济史分委员会副主任。1983年从中山大学历史学系毕业后，一直在中山大学从事明清社会经济史教学与研究。2000-2008年任中山大学历史学系主任，2008-2015年任亚太研究院常务副院长，2010-2022年任中山大学历史人类学研究中心主任。现任《中华民族交往交流交融史》编撰委员会编委、中山大学铸牢中华民族共同体意识研究基地首席专家、中华民族交往交流交融史料汇编（广东卷）编委会常务副主任。 理解中华民族共同体形成的理论基石 刘志伟最卓越的学术贡献 在于他深刻洞察到 要真正理解中华民族共同体的形成 必须摆脱长期以来 史学界对西方理论的 简单移植或被动修正 转而从中国自身的历史和文化中 提炼具有主体性 以及强大解释力的 “中国范式” 他所倡导和引领的 “历史人类学” 研究路径 正是这一学术自觉的集中体现 对于理解中华民族共同体的形成 其研究贡献主要体 现在三个方面：",
      "summary": "刘志伟，中山大学历史学系教授，中山大学人文学科发展委员会主任，国家教材委历史学科专家委员会委员，中国社会史学会副会长，中国经济史学会中国古代经济史分委员会副主任…",
      "function_tags": [
        "人物叙事"
      ],
      "writing_method": "以具体时间、数字或对象增强信息可信度。",
      "reuse_value": "高"
    },
    {
      "paragraph_id": "p004",
      "display_text": "** 一  ** ** 是探索“在历史中寻找中国”的研究路径  ** ****\n\n重塑了理解“一体”与“多元”关系的方法论\n\n他提  出历史研究的出发点应是\n\n具体的“人”在特定时空下的实践活动\n\n他带领团队深入田野\n\n将文献考证与实地访谈相结合\n\n展现了中华文化的巨大包容性和整合力\n\n证明了交往交流交融\n\n才是历史发展的主流",
      "normalized_text": "一 是探索“在历史中寻找中国”的研究路径 重塑了理解“一体”与“多元”关系的方法论 他提 出历史研究的出发点应是 具体的“人”在特定时空下的实践活动 他带领团队深入田野 将文献考证与实地访谈相结合 展现了中华文化的巨大包容性和整合力 证明了交往交流交融 才是历史发展的主流",
      "summary": "一 是探索“在历史中寻找中国”的研究路径 重塑了理解“一体”与“多元”关系的方法论 他提 出历史研究的出发点应是 具体的“人”在特定时空下的实践活动 他带领团队…",
      "function_tags": [
        "结构提示"
      ],
      "writing_method": "用引语或金句增强现场感和传播记忆。",
      "reuse_value": "高"
    },
    {
      "paragraph_id": "p005",
      "display_text": "刘志伟教授开展实地访谈\n\n** 二是以现代学术话语  **\n\n** 诠释中国传统的“食货原理”  **\n\n** 构建原创的“贡赋体制经济”理论  **\n\n为建构中国自主的知识体系\n\n作出了重要贡献\n\n他揭示了传统中国经济的运行逻辑\n\n指出市场在其中扮演着\n\n实现贡赋目标的工  具角色\n\n阐明了在近代以前\n\n统一多民族国家的内在运行机制\n\n是中国学者立足本土经验\n\n与  世界学术前沿对话的典范\n\n是中国特色哲学社会科学话语体系的\n\n重大成果\n\n** 三是通过对华南宗族的研究  **\n\n** 深刻揭示了文化认同  **\n\n** 是凝聚中华民族的强大力量  **\n\n宗族会主动地将自己的家族史\n\n与中原的士大夫谱系\n\n与王朝认可的  历史记忆相连接\n\n其研究令人信服地证明了\n\n中华民族的认同并非空洞的政治口号\n\n而是通过具体的文化实践\n\n深深植根于  历史的日常生活和实践之中\n\n四十年来\n\n他在教书育人的  岗位上\n\n** 不仅传授知识  **\n\n** 更注重培养学生的历  ** ** 史意识与民族情怀  **\n\n他指导的多位学生\n\n如今已成为史学界的中坚力量\n\n** 主编  ** ** 《中华民族交往交流交融史料汇编·广东卷》  **\n\n** 广东  ** 是中原文化向南拓展的前沿\n\n也是海上丝绸之路的门户\n\n更是观察中华民族多元一体格局",
      "normalized_text": "刘志伟教授开展实地访谈 二是以现代学术话语 诠释中国传统的“食货原理” 构建原创的“贡赋体制经济”理论 为建构中国自主的知识体系 作出了重要贡献 他揭示了传统中国经济的运行逻辑 指出市场在其中扮演着 实现贡赋目标的工 具角色 阐明了在近代以前 统一多民族国家的内在运行机制 是中国学者立足本土经验 与 世界学术前沿对话的典范 是中国特色哲学社会科学话语体系的 重大成果 三是通过对华南宗族的研究 深刻揭示了文化认同 是凝聚中华民族的强大力量 宗族会主动地将自己的家族史 与中原的士大夫谱系 与王朝认可的 历史记忆相连接 其研究令人信服地证明了 中华民族的认同并非空洞的政治口号 而是通过具体的文化实践 深深植根于 历史的日常生活和实践之中 四十年来 他在教书育人的 岗位上 不仅传授知识 更注重培养学生的历 史意识与民族情怀 他指导的多位学生 如今已成为史学界的中坚力量 主编 《中华民族交往交流交融史料汇编·广东卷》 广东 是中原文化向南拓展的前沿 也是海上丝绸之路的门户 更是观察中华民族多元一体格局",
      "summary": "刘志伟教授开展实地访谈 二是以现代学术话语 诠释中国传统的“食货原理” 构建原创的“贡赋体制经济”理论 为建构中国自主的知识体系 作出了重要贡献 他揭示了传统中…",
      "function_tags": [
        "人物叙事"
      ],
      "writing_method": "以具体时间、数字或对象增强信息可信度。",
      "reuse_value": "高"
    },
    {
      "paragraph_id": "p006",
      "display_text": "如何在一个复杂前沿地带\n\n形成和巩固的  ** 绝佳样本  **\n\n基于对广东历史这一重要性的深刻认识\n\n刘志伟主持的\n\n《中华民族交往交流交融史料汇编·  广东卷》\n\n编纂工  作立足于广东的实际\n\n旨在通过对历史文献的系统整理\n\n为理解和巩固中华民族共同体\n\n提供坚实、可信的历史依据",
      "normalized_text": "如何在一个复杂前沿地带 形成和巩固的 绝佳样本 基于对广东历史这一重要性的深刻认识 刘志伟主持的 《中华民族交往交流交融史料汇编· 广东卷》 编纂工 作立足于广东的实际 旨在通过对历史文献的系统整理 为理解和巩固中华民族共同体 提供坚实、可信的历史依据",
      "summary": "如何在一个复杂前沿地带 形成和巩固的 绝佳样本 基于对广东历史这一重要性的深刻认识 刘志伟主持的 《中华民族交往交流交融史料汇编· 广东卷》 编纂工 作立足于广…",
      "function_tags": [
        "问题引导"
      ],
      "writing_method": "用设问或悬念引导读者继续阅读。",
      "reuse_value": "高"
    },
    {
      "paragraph_id": "p007",
      "display_text": "刘志伟教授做讲座\n\n为准确把握\n\n广东中华民族交往交流交融历史\n\n** 刘志伟为编纂工作  **\n\n** 确立了三个关键的指导思路  **\n\n** 一是突出从“静态的身份”  **\n\n** 转向“动态的认同过程”  **\n\n强调在史料挖掘过程中\n\n打破静态的身份观\n\n转而聚焦于一个动态的\n\n持续不断的“认同过程”\n\n** 二是从“精英的政治”  **\n\n** 深入“民众的日常”  **\n\n在“经济互赖”中看见共同体\n\n在“礼俗融合”中看见共同体\n\n** 三是从“地方的特殊性”  **\n\n** 阐释“国家的普遍性”  **\n\n其背后反映的\n\n是中华民族形成过程中的普遍性规律\n\n因此 《广东卷》的编纂\n\n必须在呈现“特殊性”的同时\n\n时刻不忘阐释  其“普遍性”意义\n\n最终，在不到两年时间内\n\n刘志伟率领来自三所广东高校的团队\n\n高质高量完成六大分卷的史料汇编\n\n** 打造国家级中华民族共同体研究高地  **\n\n2023年，中山大学历史人类学研究中心获批\n\n第二批四部委铸牢中华民族共同体意识研究基地\n\n** 刘志伟任  **\n\n** 中山大学铸牢中华民族共同体意识研究基地  **\n\n** 首席专家  **\n\n为基地的建设与发展擘画了清晰的蓝图",
      "normalized_text": "刘志伟教授做讲座 为准确把握 广东中华民族交往交流交融历史 刘志伟为编纂工作 确立了三个关键的指导思路 一是突出从“静态的身份” 转向“动态的认同过程” 强调在史料挖掘过程中 打破静态的身份观 转而聚焦于一个动态的 持续不断的“认同过程” 二是从“精英的政治” 深入“民众的日常” 在“经济互赖”中看见共同体 在“礼俗融合”中看见共同体 三是从“地方的特殊性” 阐释“国家的普遍性” 其背后反映的 是中华民族形成过程中的普遍性规律 因此 《广东卷》的编纂 必须在呈现“特殊性”的同时 时刻不忘阐释 其“普遍性”意义 最终，在不到两年时间内 刘志伟率领来自三所广东高校的团队 高质高量完成六大分卷的史料汇编 打造国家级中华民族共同体研究高地 2023年，中山大学历史人类学研究中心获批 第二批四部委铸牢中华民族共同体意识研究基地 刘志伟任 中山大学铸牢中华民族共同体意识研究基地 首席专家 为基地的建设与发展擘画了清晰的蓝图",
      "summary": "刘志伟教授做讲座 为准确把握 广东中华民族交往交流交融历史 刘志伟为编纂工作 确立了三个关键的指导思路 一是突出从“静态的身份” 转向“动态的认同过程” 强调在…",
      "function_tags": [
        "人物叙事"
      ],
      "writing_method": "以具体时间、数字或对象增强信息可信度。",
      "reuse_value": "中"
    },
    {
      "paragraph_id": "p008",
      "display_text": "研究基地首席专家刘志伟（左）与基地主任张应强（右）合影\n\n在理论引领与范式构建上\n\n刘志伟深刻认识到\n\n铸牢中华民族共同体意识研究\n\n必须建立在中国自主的知识体系之上\n\n** 他将自己开创和引领的  **\n\n** “历史人类学”中国范式  **\n\n** 成功地转化为  **\n\n** 基地的核心研究理念和学术灵魂  **\n\n为基地在全国众多同类机构中\n\n脱颖而出\n\n形成独特优势\n\n奠定了坚实的理论基础\n\n在擘画重大工程与服务国家战略上\n\n刘志伟以身作则\n\n将学术研究落到实处\n\n除主编\n\n《中华民族交往交流交融史料汇编·\n\n广东卷》外\n\n还带领基地\n\n获  得国家社科基金\n\n铸牢专项重大项目\n\n“中华民族共同体建设的华南历史经验研究”的立项\n\n个人获国家高端智库项目\n\n《2024年国家高端智库认领课题六》\n\n此外，在刘志伟的推动下\n\n基地与来自港澳台及日本、韩国等国家和地区的高校\n\n建  立了紧密的合作关系\n\n推动跨区域跨学科合作\n\n拓展研究广度与深度",
      "normalized_text": "研究基地首席专家刘志伟（左）与基地主任张应强（右）合影 在理论引领与范式构建上 刘志伟深刻认识到 铸牢中华民族共同体意识研究 必须建立在中国自主的知识体系之上 他将自己开创和引领的 “历史人类学”中国范式 成功地转化为 基地的核心研究理念和学术灵魂 为基地在全国众多同类机构中 脱颖而出 形成独特优势 奠定了坚实的理论基础 在擘画重大工程与服务国家战略上 刘志伟以身作则 将学术研究落到实处 除主编 《中华民族交往交流交融史料汇编· 广东卷》外 还带领基地 获 得国家社科基金 铸牢专项重大项目 “中华民族共同体建设的华南历史经验研究”的立项 个人获国家高端智库项目 《2024年国家高端智库认领课题六》 此外，在刘志伟的推动下 基地与来自港澳台及日本、韩国等国家和地区的高校 建 立了紧密的合作关系 推动跨区域跨学科合作 拓展研究广度与深度",
      "summary": "研究基地首席专家刘志伟（左）与基地主任张应强（右）合影 在理论引领与范式构建上 刘志伟深刻认识到 铸牢中华民族共同体意识研究 必须建立在中国自主的知识体系之上 …",
      "function_tags": [
        "内容推进"
      ],
      "writing_method": "以具体时间、数字或对象增强信息可信度。",
      "reuse_value": "中"
    },
    {
      "paragraph_id": "p009",
      "display_text": "刘志伟讲课\n\n在团队建设与人才培养上\n\n刘志伟凝聚了一支\n\n** 跨学科高水平研究团队  **\n\n这些专家涵盖历史学、人类学、\n\n民族学、考古学等多个领域\n\n形成了强大的研究合力\n\n** 同时，他十分重视对青年学者的培养  **\n\n使基地成为培养\n\n铸牢中华民族共同体意识\n\n研究储备人才的重要平台\n\n并通过推动以境内唯一一个\n\nCSSCI及THCI双核心期刊\n\n《历史人类学学刊》\n\n为代表的学术阵地建设\n\n扩大中国研究的话语影响\n\n刘志伟以历史研究\n\n阐释中华民族共同体形成逻辑\n\n以国家工程夯实民族团结历史根基\n\n以平台建设服务新时代民族工作\n\n以学术实践深刻体现\n\n“促进各民族像石榴籽一样紧紧抱在一起”\n\n的重要思想\n\n为全国尤其是广东省民族团结进步事业\n\n作出了重要贡献\n\n让我们一起致敬，学习！\n\n**",
      "normalized_text": "刘志伟讲课 在团队建设与人才培养上 刘志伟凝聚了一支 跨学科高水平研究团队 这些专家涵盖历史学、人类学、 民族学、考古学等多个领域 形成了强大的研究合力 同时，他十分重视对青年学者的培养 使基地成为培养 铸牢中华民族共同体意识 研究储备人才的重要平台 并通过推动以境内唯一一个 CSSCI及THCI双核心期刊 《历史人类学学刊》 为代表的学术阵地建设 扩大中国研究的话语影响 刘志伟以历史研究 阐释中华民族共同体形成逻辑 以国家工程夯实民族团结历史根基 以平台建设服务新时代民族工作 以学术实践深刻体现 “促进各民族像石榴籽一样紧紧抱在一起” 的重要思想 为全国尤其是广东省民族团结进步事业 作出了重要贡献 让我们一起致敬，学习！",
      "summary": "刘志伟讲课 在团队建设与人才培养上 刘志伟凝聚了一支 跨学科高水平研究团队 这些专家涵盖历史学、人类学、 民族学、考古学等多个领域 形成了强大的研究合力 同时，…",
      "function_tags": [
        "问题引导"
      ],
      "writing_method": "用设问或悬念引导读者继续阅读。",
      "reuse_value": "中"
    }
  ],
  "structural_notes": [],
  "style": {
    "labels": [
      "事实驱动",
      "分章节叙事",
      "校媒报道"
    ],
    "tone": "准确、清晰、具有公共价值导向",
    "sentence_features": [
      "关键信息前置",
      "长短句结合",
      "专业信息配合通俗解释"
    ],
    "layout_features": [
      "小标题划分主题",
      "图片与事实段落交替",
      "重点信息加粗"
    ],
    "common_phrases": [
      "中山大学",
      "中大",
      "欢迎关注",
      "共同见证"
    ],
    "rhetorical_devices": [
      "设问",
      "排比",
      "图文证明",
      "价值收束"
    ],
    "style_metrics": {
      "headline_emotion_level": 4,
      "fact_density": "high",
      "quote_density": "medium",
      "value_sublimation_level": "medium",
      "average_paragraph_length": "short-medium",
      "bold_usage": "key_information_highlight",
      "image_caption_dependency": "medium"
    },
    "reusable_phrases": [
      "围绕主题展开事实",
      "以图文呈现现场",
      "在结尾完成价值收束"
    ],
    "not_reusable_phrases": [
      "10月14日上午，全省民族团结进步表彰大会在广州召开，表彰广东省民族团结进步模范集体和模范个人。",
      "研究基地首席专家刘志伟（左）与基地主任张应强（右）合影 在理论引领与范式构建上 刘志伟深刻认识到 铸牢中华民族共同体意识研究 必须建立在中国自主的知识体系之上 他将自己开创和引领的 “历史人类学”中国范式 成功地转化为 基地的核心研究理念和学术灵魂 为基地在全国众多同类机构中 脱颖而出 形成独特优势 奠定了坚实的理论基础 在擘画重大工程与服务国家战略上 刘志伟以身作则 将学术研究落到实处 除主编 《中华民族交往交流交融史料汇编· 广东卷"
    ]
  },
  "value_narrative": {
    "themes": [
      "刘志伟",
      "民族团结进步",
      "历史人类学",
      "中华民族共同体"
    ],
    "levels": {
      "personal_level": "在正文有人物时，以其行动、选择或专业成长承载叙事。",
      "team_level": "以团队或机构协作说明成果形成过程。",
      "course_level": "仅在正文涉及课程或教学实践时使用。",
      "school_level": "将具体事件和成果连接到中山大学的科研、育人或社会服务能力。",
      "national_level": "仅依据正文，将成果连接到国家战略、公共利益或国际交流。"
    },
    "transition_method": "从可核验的个人、团队或事件事实逐层过渡到学校与公共价值。",
    "school_image": [
      "严谨务实",
      "开放协同",
      "服务社会"
    ],
    "ending_method": "以正文支持的成果、愿景或公共价值收束，不追加无来源口号。"
  },
  "visuals": [
    {
      "image_id": "cover",
      "caption": "封面图",
      "caption_source": "structural",
      "type": "封面图",
      "function": "建立文章主题和视觉入口",
      "position": "标题前"
    },
    {
      "image_id": "img001",
      "caption": "动态视觉",
      "caption_source": "structural",
      "type": "动态视觉",
      "function": "分隔内容并保留公众号阅读节奏",
      "position": "正文前"
    },
    {
      "image_id": "img002",
      "caption": "正文图片2",
      "caption_source": "inferred",
      "type": "正文图片",
      "function": "辅助呈现正文事实和现场氛围",
      "position": "p001后"
    },
    {
      "image_id": "img003",
      "caption": "正文图片3",
      "caption_source": "inferred",
      "type": "正文图片",
      "function": "辅助呈现正文事实和现场氛围",
      "position": "p002后"
    },
    {
      "image_id": "img004",
      "caption": "正文图片4",
      "caption_source": "inferred",
      "type": "正文图片",
      "function": "辅助呈现正文事实和现场氛围",
      "position": "p004后"
    },
    {
      "image_id": "img005",
      "caption": "正文图片5",
      "caption_source": "inferred",
      "type": "正文图片",
      "function": "辅助呈现正文事实和现场氛围",
      "position": "p006后"
    },
    {
      "image_id": "img006",
      "caption": "正文图片6",
      "caption_source": "inferred",
      "type": "正文图片",
      "function": "辅助呈现正文事实和现场氛围",
      "position": "p007后"
    },
    {
      "image_id": "img007",
      "caption": "正文图片7",
      "caption_source": "inferred",
      "type": "正文图片",
      "function": "辅助呈现正文事实和现场氛围",
      "position": "p008后"
    }
  ],
  "image_stats": {
    "cover_images": 1,
    "content_images": 6,
    "decorative_images": 1,
    "recommendation_images": 0,
    "footer_images": 0,
    "total_image_nodes_in_clean": 8,
    "unique_image_urls": 8
  },
  "templates": [
    {
      "template": "事实导入 -> 分章节展开人物、方法或成果 -> 数据与案例支撑 -> 回到学校贡献或公共价值",
      "applicable_scenarios": [
        "高校会议、科研成果、人物荣誉、育人成果等事实型报道"
      ],
      "not_applicable_scenarios": [
        "缺少可核验事实的纯海报、纯情绪文案或招生政策原文"
      ]
    },
    {
      "template": "核心结果前置 -> 解释问题背景 -> 拆解关键机制 -> 呈现实践效果 -> 给出有来源的价值收束",
      "applicable_scenarios": [
        "需要兼顾专业信息与公众可读性的校园融媒文章"
      ],
      "not_applicable_scenarios": [
        "不能公开过程数据、人物身份或结果依据的内容"
      ]
    }
  ],
  "generation_constraints": {
    "must_not_invent": [
      "人物姓名、职务、机构、时间、数字、奖项、论文、项目及直接引语",
      "图片中未被正文或原始图注明确表达的信息"
    ],
    "strong_claims_require_source": [
      "精确日期和数字",
      "获奖、入选、首创、首次、最高、最大等官方或比较性声明",
      "论文发表、项目立项、机构职务和政策平台名称"
    ],
    "quote_handling": [
      "直接引语必须保持原意并标明说话人",
      "允许去除Markdown样式和多余空白，不得拼接改写为新的引语"
    ],
    "scenario_boundaries": [
      "仅适用于有完整正文和可回链证据的文本型推文",
      "不得使用推荐阅读、iSYSU、编辑链、二维码或评论区内容"
    ],
    "recommended_writer_use": [
      "按structure组织章节",
      "从facts选择与目标章节匹配的证据",
      "强声明逐项核对source_quote"
    ],
    "type_specific_constraints": [
      {
        "term": "正文事实",
        "constraint": "每个实质章节至少使用一条可回链事实，长文不得受固定事实条数限制。",
        "category": "must_not_invent"
      },
      {
        "term": "推荐阅读硬截止",
        "constraint": "首次推荐阅读标记及其后全部内容不得进入写作素材。",
        "category": "scenario_boundary"
      }
    ]
  }
}